{
  "id": "api/data/EntityMetadata",
  "title": "EntityMetadata",
  "contents": "\n\n<article>\n  <div class=\"github-links\">\n  <a href=\"https://github.com/ngrx/platform/edit/master/modules/data/src/entity-metadata/entity-metadata.ts?message=docs(data)%3A%20describe%20your%20change...#L11-L21\" aria-label=\"Suggest Edits\" title=\"Suggest Edits\"><i class=\"material-icons\" aria-hidden=\"true\" role=\"img\">mode_edit</i></a>\n  <a href=\"https://github.com/ngrx/platform/tree/8.0.0/modules/data/src/entity-metadata/entity-metadata.ts#L11-L21\" aria-label=\"View Source\" title=\"View Source\"><i class=\"material-icons\" aria-hidden=\"true\" role=\"img\">code</i></a>\n</div>\n  <div class=\"breadcrumb\">\n    <script type=\"application/ld+json\">\n      {\n        \"@context\": \"http://schema.org\",\n        \"@type\": \"BreadcrumbList\",\n        \"itemListElement\": [\n          { \"@type\": \"ListItem\", \"position\": 1, \"item\": { \"@id\": \"https://ngrx.io//api\", \"name\": \"API\" } },\n          { \"@type\": \"ListItem\", \"position\": 2, \"item\": { \"@id\": \"https://ngrx.io/api/data\", \"name\": \"@ngrx/data\" } },\n          { \"@type\": \"ListItem\", \"position\": 3, \"item\": { \"@id\": \"https://ngrx.io/api/data/EntityMetadata\", \"name\": \"EntityMetadata\" } }\n        ]\n      }\n    </script>\n      <a href=\"/api\">API</a> > <a href=\"api/data\">@ngrx/data</a>\n  </div>\n  \n  <header class=\"api-header\">\n    <h1 id=\"entitymetadata\">EntityMetadata<a title=\"Link to this heading\" class=\"header-link\" aria-hidden=\"true\" href=\"api/data/EntityMetadata#entitymetadata\"><i class=\"material-icons\">link</i></a></h1>\n    <label class=\"api-type-label interface\">interface</label>\n    \n    \n    \n  </header>\n  \n  <aio-toc class=\"embedded\"></aio-toc>\n\n  <div class=\"api-body\">\n    \n  <section class=\"short-description\">\n    <p>Metadata that describe an entity type and its collection to ngrx-data</p>\n\n    \n  </section>\n  \n  \n  <section class=\"interface-overview\">\n<code-example language=\"ts\" hidecopy=\"true\">\ninterface <a href=\"api/data/EntityMetadata\" class=\"code-anchor\">EntityMetadata</a>&#x3C;T, S> {\n  <a class=\"code-anchor\" href=\"api/data/EntityMetadata#entityName\"><span class=\"member-name\">entityName</span>: string</a>\n  <a class=\"code-anchor\" href=\"api/data/EntityMetadata#entityDispatcherOptions\"><span class=\"member-name\">entityDispatcherOptions</span>?: Partial&#x3C;EntityDispatcherDefaultOptions></a>\n  <a class=\"code-anchor\" href=\"api/data/EntityMetadata#filterFn\"><span class=\"member-name\">filterFn</span>?: EntityFilterFn&#x3C;T></a>\n  <a class=\"code-anchor\" href=\"api/data/EntityMetadata#noChangeTracking\"><span class=\"member-name\">noChangeTracking</span>?: boolean</a>\n  <a class=\"code-anchor\" href=\"api/data/EntityMetadata#selectId\"><span class=\"member-name\">selectId</span>?: IdSelector&#x3C;T></a>\n  <a class=\"code-anchor\" href=\"api/data/EntityMetadata#sortComparer\"><span class=\"member-name\">sortComparer</span>?: false | Comparer&#x3C;T></a>\n  <a class=\"code-anchor\" href=\"api/data/EntityMetadata#additionalCollectionState\"><span class=\"member-name\">additionalCollectionState</span>?: S</a>\n}\n</code-example>\n\n  \n  \n\n\n  \n  \n\n</section>\n  \n\n  \n  \n  \n<section class=\"instance-properties\">\n  <h2 id=\"properties\">Properties<a title=\"Link to this heading\" class=\"header-link\" aria-hidden=\"true\" href=\"api/data/EntityMetadata#properties\"><i class=\"material-icons\">link</i></a></h2>\n  <table class=\"is-full-width list-table property-table\">\n    <thead>\n      <tr>\n        <th>Property</th>\n        <th>Description</th>\n      </tr>\n    </thead>\n    <tbody>\n    \n      <tr class=\"instance-property\">\n        <td>\n          <a id=\"entityName\"></a>\n          <code><span class=\"member-name\">entityName</span>: string</code>\n        </td>\n        <td>\n          \n          \n          \n        </td>\n    </tr>\n    \n      <tr class=\"instance-property\">\n        <td>\n          <a id=\"entityDispatcherOptions\"></a>\n          <code><span class=\"member-name\">entityDispatcherOptions</span>?: Partial&#x3C;<a href=\"api/data/EntityDispatcherDefaultOptions\" class=\"code-anchor\">EntityDispatcherDefaultOptions</a>></code>\n        </td>\n        <td>\n          \n          \n          \n        </td>\n    </tr>\n    \n      <tr class=\"instance-property\">\n        <td>\n          <a id=\"filterFn\"></a>\n          <code><span class=\"member-name\"><a href=\"api/data/EntityMetadata#filterFn\" class=\"code-anchor\">filterFn</a></span>?: <a href=\"api/data/EntityFilterFn\" class=\"code-anchor\">EntityFilterFn</a>&#x3C;T></code>\n        </td>\n        <td>\n          \n          \n          \n        </td>\n    </tr>\n    \n      <tr class=\"instance-property\">\n        <td>\n          <a id=\"noChangeTracking\"></a>\n          <code><span class=\"member-name\">noChangeTracking</span>?: boolean</code>\n        </td>\n        <td>\n          \n          \n          \n        </td>\n    </tr>\n    \n      <tr class=\"instance-property\">\n        <td>\n          <a id=\"selectId\"></a>\n          <code><span class=\"member-name\">selectId</span>?: <a href=\"api/entity/IdSelector\" class=\"code-anchor\">IdSelector</a>&#x3C;T></code>\n        </td>\n        <td>\n          \n          \n          \n        </td>\n    </tr>\n    \n      <tr class=\"instance-property\">\n        <td>\n          <a id=\"sortComparer\"></a>\n          <code><span class=\"member-name\">sortComparer</span>?: false | <a href=\"api/entity/Comparer\" class=\"code-anchor\">Comparer</a>&#x3C;T></code>\n        </td>\n        <td>\n          \n          \n          \n        </td>\n    </tr>\n    \n      <tr class=\"instance-property\">\n        <td>\n          <a id=\"additionalCollectionState\"></a>\n          <code><span class=\"member-name\"><a href=\"api/data/EntityMetadata#additionalCollectionState\" class=\"code-anchor\">additionalCollectionState</a></span>?: S</code>\n        </td>\n        <td>\n          \n          \n          \n        </td>\n    </tr>\n    \n    </tbody>\n  </table>\n</section>\n  \n\n\n  \n\n\n  </div>\n</article>\n\n<!-- links to this doc:\n - api/data\n - api/data/EntityDefinition\n - api/data/EntityDefinitionService\n - api/data/EntityMetadataMap\n - api/data/EntitySelectorsFactory\n - api/data/createEntityDefinition\n - guide/data/entity-metadata\n - guide/data/extension-points\n - guide/data/limitations\n-->\n<!-- links from this doc:\n - /api\n - api/data\n - api/data/EntityDispatcherDefaultOptions\n - api/data/EntityFilterFn\n - api/data/EntityMetadata#additionalCollectionState\n - api/data/EntityMetadata#entityDispatcherOptions\n - api/data/EntityMetadata#entityName\n - api/data/EntityMetadata#entitymetadata\n - api/data/EntityMetadata#filterFn\n - api/data/EntityMetadata#noChangeTracking\n - api/data/EntityMetadata#properties\n - api/data/EntityMetadata#selectId\n - api/data/EntityMetadata#sortComparer\n - api/entity/Comparer\n - api/entity/IdSelector\n - https://github.com/ngrx/platform/edit/master/modules/data/src/entity-metadata/entity-metadata.ts?message=docs(data)%3A%20describe%20your%20change...#L11-L21\n - https://github.com/ngrx/platform/tree/8.0.0/modules/data/src/entity-metadata/entity-metadata.ts#L11-L21\n-->"
}